combus/__init__.py
combus/command.py
combus/command_bus.py
combus/command_handler.py
combus/test/__init__.py
combus/test/test_command.py
combus-0.1.0.dist-info/METADATA
combus-0.1.0.dist-info/RECORD
combus-0.1.0.dist-info/WHEEL
combus-0.1.0.dist-info/top_level.txt
