Metadata-Version: 2.1
Name: combus
Version: 0.1.0
Summary: Command & Handle
Home-page: https://github.com/fowbi/combus
Author: Fowbi
Author-email: tobi@magier.be
License: MIT
Platform: UNKNOWN
Classifier: Development Status :: 3 - Alpha
Classifier: Intended Audience :: Developers
Classifier: License :: OSI Approved :: MIT License
Classifier: Natural Language :: English
Classifier: Programming Language :: Python :: 3.7
